{
  "name": "ghostpdl",
  "owner": "ArtifexSoftware",
  "created_at": "2020-05-06T09:56:06Z",
  "updated_at": "2025-01-13T17:29:24Z",
  "pushed_at": "2025-01-10T16:01:25Z",
  "size": 276983,
  "stars": 126,
  "forks": 48,
  "open_issues": 1,
  "watchers": 126,
  "has_security_policy": false,
  "default_branch": "master",
  "protected_branches": [],
  "languages": {
    "C": 65853145,
    "HTML": 6827669,
    "Makefile": 3320200,
    "Shell": 3241000,
    "PostScript": 1795895,
    "Roff": 850792,
    "Python": 505519,
    "C++": 433555,
    "M4": 426324,
    "CMake": 363825,
    "Pascal": 166409,
    "Rez": 109990,
    "Perl": 107708,
    "DIGITAL Command Language": 103897,
    "Tcl": 89463,
    "Ada": 89080,
    "TeX": 87893,
    "JavaScript": 70255,
    "C#": 54009,
    "Awk": 52809,
    "Papyrus": 38163,
    "Module Management System": 34521,
    "CSS": 31527,
    "Assembly": 26353,
    "Batchfile": 26069,
    "WebAssembly": 21044,
    "GLSL": 18225,
    "SAS": 16402,
    "XC": 15647,
    "Meson": 15152,
    "NSIS": 14817,
    "Smalltalk": 10159,
    "Yacc": 8818,
    "Scilab": 7694,
    "Inno Setup": 6431,
    "Visual Basic .NET": 6028,
    "Lex": 2749,
    "Dockerfile": 1058,
    "QMake": 486,
    "Standard ML": 232,
    "Scala": 153
  },
  "commit_activity": {
    "total_commits_last_year": 254,
    "avg_commits_per_week": 4.884615384615385,
    "days_active_last_year": 128
  },
  "security_features": {
    "has_security_policy": false,
    "has_protected_branches": false,
    "has_wiki": true,
    "has_issues": false,
    "allow_forking": true,
    "is_template": false,
    "license": "other"
  },
  "collected_at": "2025-01-14T13:57:38.286582"
}