{
  "name": "buildah",
  "owner": "containers",
  "created_at": "2017-01-26T16:59:13Z",
  "updated_at": "2025-01-14T02:03:52Z",
  "pushed_at": "2025-01-13T22:05:13Z",
  "size": 64932,
  "stars": 7559,
  "forks": 788,
  "open_issues": 154,
  "watchers": 7559,
  "has_security_policy": false,
  "default_branch": "main",
  "protected_branches": [
    "main",
    "release-1.15",
    "release-1.16",
    "release-1.17",
    "release-1.18",
    "release-1.19",
    "release-1.20",
    "release-1.21",
    "release-1.22",
    "release-1.23",
    "release-1.24",
    "release-1.26",
    "release-1.27",
    "release-1.28",
    "release-1.29",
    "release-1.31",
    "release-1.32"
  ],
  "languages": {
    "Go": 1590529,
    "Shell": 691658,
    "Dockerfile": 15097,
    "Perl": 10721,
    "Makefile": 9496,
    "Nix": 5816,
    "Roff": 1045,
    "Awk": 512,
    "Assembly": 431
  },
  "commit_activity": {
    "total_commits_last_year": 378,
    "avg_commits_per_week": 7.269230769230769,
    "days_active_last_year": 178
  },
  "security_features": {
    "has_security_policy": false,
    "has_protected_branches": true,
    "has_wiki": false,
    "has_issues": true,
    "allow_forking": true,
    "is_template": false,
    "license": "apache-2.0"
  },
  "collected_at": "2025-01-14T12:56:06.530098"
}