{
  "name": "discourse-bbcode",
  "owner": "discourse",
  "created_at": "2014-08-25T09:01:39Z",
  "updated_at": "2024-11-28T14:50:04Z",
  "pushed_at": "2024-11-28T14:50:01Z",
  "size": 464,
  "stars": 12,
  "forks": 23,
  "open_issues": 0,
  "watchers": 12,
  "has_security_policy": false,
  "default_branch": "main",
  "protected_branches": [
    "main"
  ],
  "languages": {
    "JavaScript": 5441,
    "Ruby": 5320,
    "SCSS": 223
  },
  "commit_activity": {
    "total_commits_last_year": 0,
    "avg_commits_per_week": 0,
    "days_active_last_year": 0
  },
  "security_features": {
    "has_security_policy": false,
    "has_protected_branches": true,
    "has_wiki": false,
    "has_issues": false,
    "allow_forking": true,
    "is_template": false,
    "license": "mit"
  },
  "collected_at": "2025-01-14T22:54:50.930441"
}