{
  "name": "hive",
  "owner": "openshift",
  "created_at": "2018-09-13T18:47:21Z",
  "updated_at": "2025-01-10T19:03:30Z",
  "pushed_at": "2025-01-11T08:50:49Z",
  "size": 143932,
  "stars": 256,
  "forks": 243,
  "open_issues": 20,
  "watchers": 256,
  "has_security_policy": false,
  "default_branch": "master",
  "protected_branches": [
    "cmm",
    "master",
    "mce-2.1",
    "mce-2.2"
  ],
  "languages": {
    "Go": 4251252,
    "Shell": 74855,
    "Python": 33789,
    "Makefile": 13384,
    "Dockerfile": 3211
  },
  "commit_activity": {
    "total_commits_last_year": 0,
    "avg_commits_per_week": 0,
    "days_active_last_year": 0
  },
  "security_features": {
    "has_security_policy": false,
    "has_protected_branches": true,
    "has_wiki": false,
    "has_issues": true,
    "allow_forking": true,
    "is_template": false,
    "license": "apache-2.0"
  },
  "collected_at": "2025-01-14T19:47:21.409934"
}