{
  "name": "play-with-docker",
  "owner": "play-with-docker",
  "created_at": "2016-10-08T01:10:47Z",
  "updated_at": "2025-01-09T16:03:40Z",
  "pushed_at": "2024-12-20T05:05:08Z",
  "size": 3335,
  "stars": 3006,
  "forks": 732,
  "open_issues": 98,
  "watchers": 3006,
  "has_security_policy": false,
  "default_branch": "master",
  "protected_branches": [],
  "languages": {
    "JavaScript": 474188,
    "Go": 282449,
    "HTML": 63810,
    "Shell": 17882,
    "CSS": 7651,
    "Dockerfile": 6853,
    "PowerShell": 3225,
    "Vim Script": 170
  },
  "commit_activity": {
    "total_commits_last_year": 0,
    "avg_commits_per_week": 0,
    "days_active_last_year": 0
  },
  "security_features": {
    "has_security_policy": false,
    "has_protected_branches": false,
    "has_wiki": true,
    "has_issues": true,
    "allow_forking": true,
    "is_template": false,
    "license": "mit"
  },
  "collected_at": "2025-01-14T15:13:45.167251"
}