{
  "name": "shadow",
  "owner": "shadow-maint",
  "created_at": "2013-06-05T17:13:45Z",
  "updated_at": "2025-01-14T11:09:27Z",
  "pushed_at": "2025-01-14T11:09:22Z",
  "size": 22648,
  "stars": 314,
  "forks": 240,
  "open_issues": 119,
  "watchers": 314,
  "has_security_policy": false,
  "default_branch": "master",
  "protected_branches": [
    "4.1.4.3",
    "4.14.x",
    "4.15.x",
    "master"
  ],
  "languages": {
    "Shell": 1668390,
    "C": 1263044,
    "Python": 46991,
    "M4": 27473,
    "Yacc": 22719,
    "Makefile": 17253,
    "Perl": 3114
  },
  "commit_activity": {
    "total_commits_last_year": 353,
    "avg_commits_per_week": 6.788461538461538,
    "days_active_last_year": 135
  },
  "security_features": {
    "has_security_policy": false,
    "has_protected_branches": true,
    "has_wiki": true,
    "has_issues": true,
    "allow_forking": true,
    "is_template": false,
    "license": "other"
  },
  "collected_at": "2025-01-14T13:32:27.408125"
}