{
  "name": "solara",
  "owner": "widgetti",
  "created_at": "2022-03-09T08:12:01Z",
  "updated_at": "2025-01-14T08:15:45Z",
  "pushed_at": "2025-01-13T23:16:38Z",
  "size": 38625,
  "stars": 1960,
  "forks": 145,
  "open_issues": 266,
  "watchers": 1960,
  "has_security_policy": false,
  "default_branch": "master",
  "protected_branches": [],
  "languages": {
    "Python": 1175090,
    "Vue": 126138,
    "CSS": 93997,
    "JavaScript": 34728,
    "Jinja": 26239,
    "TypeScript": 18475,
    "HTML": 10325,
    "Jupyter Notebook": 3758,
    "Shell": 2466,
    "Procfile": 1038
  },
  "commit_activity": {
    "total_commits_last_year": 0,
    "avg_commits_per_week": 0,
    "days_active_last_year": 0
  },
  "security_features": {
    "has_security_policy": false,
    "has_protected_branches": false,
    "has_wiki": true,
    "has_issues": true,
    "allow_forking": true,
    "is_template": false,
    "license": "mit"
  },
  "collected_at": "2025-01-14T18:51:48.287793"
}