{
  "name": "primecoin",
  "owner": "Ziftr",
  "created_at": "2014-11-12T21:10:11Z",
  "updated_at": "2014-11-12T21:59:17Z",
  "pushed_at": "2015-02-09T20:36:28Z",
  "size": 22684,
  "stars": 0,
  "forks": 1,
  "open_issues": 0,
  "watchers": 0,
  "has_security_policy": false,
  "default_branch": "master",
  "protected_branches": [],
  "languages": {
    "TypeScript": 5239328,
    "C++": 2524523,
    "C": 90596,
    "Python": 69704,
    "Shell": 13170,
    "Objective-C++": 2734,
    "CSS": 1127
  },
  "commit_activity": {
    "total_commits_last_year": 0,
    "avg_commits_per_week": 0,
    "days_active_last_year": 0
  },
  "security_features": {
    "has_security_policy": false,
    "has_protected_branches": false,
    "has_wiki": true,
    "has_issues": false,
    "allow_forking": true,
    "is_template": false,
    "license": "other"
  },
  "collected_at": "2025-01-14T18:56:26.448424"
}